README.md
setup.py
cloud_resumable_upload/__init__.py
cloud_resumable_upload/cloud_resumable_upload.py
cloud_resumable_upload.egg-info/PKG-INFO
cloud_resumable_upload.egg-info/SOURCES.txt
cloud_resumable_upload.egg-info/dependency_links.txt
cloud_resumable_upload.egg-info/requires.txt
cloud_resumable_upload.egg-info/top_level.txt