Metadata-Version: 2.1
Name: cloud-resumable-upload
Version: 1.0.dev0
Summary: Upload documents from the cloud to the cloud without time out error.
Home-page: https://github.com/sbi-rviot/cloud_resumable_upload
Author: Renaud Viot
Author-email: renaud.viot@simply-bi.com
License: UNKNOWN
Platform: UNKNOWN
Classifier: Programming Language :: Python :: 3
Classifier: License :: OSI Approved :: MIT License
Classifier: Operating System :: OS Independent
